ci/doc.yml
ci/environment.yml
datatree/__init__.py
datatree/_version.py
datatree/common.py
datatree/datatree.py
datatree/extensions.py
datatree/formatting.py
datatree/formatting_html.py
datatree/io.py
datatree/iterators.py
datatree/mapping.py
datatree/ops.py
datatree/py.typed
datatree/render.py
datatree/testing.py
datatree/treenode.py
datatree/tests/__init__.py
datatree/tests/conftest.py
datatree/tests/test_dataset_api.py
datatree/tests/test_datatree.py
datatree/tests/test_extensions.py
datatree/tests/test_formatting.py
datatree/tests/test_formatting_html.py
datatree/tests/test_io.py
datatree/tests/test_mapping.py
datatree/tests/test_treenode.py
datatree/tests/test_version.py
xarray_datatree-0.0.14.dist-info/LICENSE
xarray_datatree-0.0.14.dist-info/METADATA
xarray_datatree-0.0.14.dist-info/WHEEL
xarray_datatree-0.0.14.dist-info/top_level.txt
xarray_datatree-0.0.14.dist-info/RECORD
