Metadata-Version: 2.1
Name: xarray-datatree
Version: 0.0.14
Summary: Hierarchical tree-like data structures for xarray
Author-email: Thomas Nicholas <thomas.nicholas@columbia.edu>
License: Apache-2
Project-URL: Home, https://github.com/xarray-contrib/datatree
Project-URL: Documentation, https://xarray-datatree.readthedocs.io/en/stable/
Classifier: Development Status :: 3 - Alpha
Classifier: Intended Audience :: Science/Research
Classifier: Topic :: Scientific/Engineering
Classifier: License :: OSI Approved :: Apache Software License
Classifier: Operating System :: OS Independent
Classifier: Programming Language :: Python
Classifier: Programming Language :: Python :: 3.9
Classifier: Programming Language :: Python :: 3.10
Classifier: Programming Language :: Python :: 3.11
Requires-Python: >=3.9
License-File: LICENSE
Requires-Dist: xarray>=2023.12.0
Requires-Dist: packaging
